{
  "trackingCodes": [
    {
      "code": "TESTE123",
      "city": "Rio de Janeiro",
      "createdAt": 1719619200000,
      "currentStep": 11,
      "hasFailed": false,
      "hasRandomEvent": false,
      "history": [
        {
          "status": "CRIADO",
          "timestamp": "29/06/2025 08:00:00",
          "description": "Pedido aprovado! Aguarde os demais status de rastreamento."
        },
        {
          "status": "POSTADO",
          "timestamp": "29/06/2025 10:00:00",
          "description": "O seu pedido foi postado com sucesso."
        },
        {
          "status": "📦 DESPACHADO",
          "timestamp": "29/06/2025 12:00:00",
          "description": "O produto foi despachado da unidade de origem."
        },
        {
          "status": "🚚 EM TRÂNSITO LOCAL",
          "timestamp": "30/06/2025 09:00:00",
          "description": "O produto está em trânsito local."
        },
        {
          "status": "🏢 CHEGOU NO CENTRO DE DISTRIBUIÇÃO",
          "timestamp": "01/07/2025 08:30:00",
          "description": "O produto chegou ao centro de distribuição."
        },
        {
          "status": "🛠️ PREPARANDO PARA SAIR",
          "timestamp": "01/07/2025 15:00:00",
          "description": "O produto está sendo preparado para sair."
        },
        {
          "status": "🚛 PACOTE EM TRÂNSITO",
          "timestamp": "02/07/2025 09:30:00",
          "description": "O pacote está em trânsito para a cidade de destino. Destino: Rio de Janeiro."
        },
        {
          "status": "📍 PACOTE CHEGOU NA CIDADE Destino",
          "timestamp": "03/07/2025 08:00:00",
          "description": "O pacote chegou em Rio de Janeiro."
        },
        {
          "status": "📬 PACOTE PRONTO PARA ENTREGA",
          "timestamp": "03/07/2025 13:00:00",
          "description": "O pacote está pronto para entrega."
        },
        {
          "status": "🏃‍♂️ SAIU PARA ENTREGA",
          "timestamp": "04/07/2025 09:00:00",
          "description": "O pacote saiu para entrega. Destino: Rio de Janeiro."
        },
        {
          "status": "🔄 SAINDO PARA ENTREGA",
          "timestamp": "04/07/2025 13:30:00",
          "description": "O pacote está saindo para entrega novamente. Destino: Rio de Janeiro."
        },
        {
          "status": "✅ ENTREGUE",
          "timestamp": "04/07/2025 17:00:00",
          "description": "O pacote foi entregue ao destinatário."
        }
      ]
    }
  ]
}